odoo/addons/account_operating_unit/README.rst
odoo/addons/account_operating_unit/__init__.py
odoo/addons/account_operating_unit/__manifest__.py
odoo/addons/account_operating_unit/i18n/account_operating_unit.pot
odoo/addons/account_operating_unit/models/__init__.py
odoo/addons/account_operating_unit/models/account_journal.py
odoo/addons/account_operating_unit/models/account_move.py
odoo/addons/account_operating_unit/models/account_payment.py
odoo/addons/account_operating_unit/models/res_company.py
odoo/addons/account_operating_unit/readme/CONFIGURE.rst
odoo/addons/account_operating_unit/readme/CONTRIBUTORS.rst
odoo/addons/account_operating_unit/readme/DESCRIPTION.rst
odoo/addons/account_operating_unit/readme/ROADMAP.rst
odoo/addons/account_operating_unit/readme/USAGE.rst
odoo/addons/account_operating_unit/report/__init__.py
odoo/addons/account_operating_unit/report/account_invoice_report.py
odoo/addons/account_operating_unit/security/account_security.xml
odoo/addons/account_operating_unit/static/description/icon.png
odoo/addons/account_operating_unit/static/description/index.html
odoo/addons/account_operating_unit/tests/__init__.py
odoo/addons/account_operating_unit/tests/test_account_operating_unit.py
odoo/addons/account_operating_unit/tests/test_cross_ou_journal_entry.py
odoo/addons/account_operating_unit/tests/test_invoice_operating_unit.py
odoo/addons/account_operating_unit/tests/test_operating_unit_security.py
odoo/addons/account_operating_unit/tests/test_payment_operating_unit.py
odoo/addons/account_operating_unit/views/account_invoice_report_view.xml
odoo/addons/account_operating_unit/views/account_journal_view.xml
odoo/addons/account_operating_unit/views/account_move_view.xml
odoo/addons/account_operating_unit/views/account_payment_view.xml
odoo/addons/account_operating_unit/views/company_view.xml
odoo13_addon_account_operating_unit-13.0.1.2.0.dist-info/METADATA
odoo13_addon_account_operating_unit-13.0.1.2.0.dist-info/WHEEL
odoo13_addon_account_operating_unit-13.0.1.2.0.dist-info/top_level.txt
odoo13_addon_account_operating_unit-13.0.1.2.0.dist-info/RECORD
