Metadata-Version: 2.1
Name: odoo13-addon-account-operating-unit
Version: 13.0.1.2.0
Summary: Introduces Operating Unit (OU) in invoices and Accounting Entries with clearing account
Home-page: https://github.com/OCA/operating-unit
Author: Eficent, Serpent Consulting Services Pvt. Ltd.,WilldooIT Pty Ltd,Odoo Community Association (OCA)
Author-email: support@odoo-community.org
License: LGPL-3
Platform: UNKNOWN
Classifier: Programming Language :: Python
Classifier: Framework :: Odoo
Classifier: License :: OSI Approved :: GNU Lesser General Public License v3 (LGPLv3)
Requires-Python: >=3.5
Requires-Dist: odoo13-addon-operating-unit
Requires-Dist: odoo (<13.1dev,>=13.0a)
